FlaskSaml/FlaskSP.py
FlaskSaml/__init__.py
FlaskSaml/flask_utils.py
FlaskSaml/reqID.py
FlaskSamlSP-22.8.28.dist-info/LICENSE.txt
FlaskSamlSP-22.8.28.dist-info/METADATA
FlaskSamlSP-22.8.28.dist-info/WHEEL
FlaskSamlSP-22.8.28.dist-info/top_level.txt
FlaskSamlSP-22.8.28.dist-info/RECORD
