Metadata-Version: 2.1
Name: FlaskSamlSP
Version: 22.8.28
Summary: A SAML Service Provider Blueprint for Flask Applications
Home-page: https://github.com/Glocktober/FlaskSamlSP
Author: gunville
Author-email: rk13088@yahoo.com
Project-URL: repo, https://github.com/Glocktober/FlaskSamlSP.git
Project-URL: overview, https://github.com/Glocktober/FlaskSamlSP/blob/master/README.md
Keywords: 'saml2 flask'
Classifier: Programming Language :: Python :: 3
Classifier: License :: OSI Approved :: MIT License
Classifier: Operating System :: OS Independent
Requires-Python: >=3.6
License-File: LICENSE.txt
Requires-Dist: Flask (>=2.0.0)
Requires-Dist: Flask-Session (>=0.4.0)
Requires-Dist: minisaml (==21.10)
